radiusauth/__init__.py
radiusauth/backends/__init__.py
radiusauth/backends/radius.py
django_radius_nofuture-1.5.0.dev1.dist-info/LICENSE
django_radius_nofuture-1.5.0.dev1.dist-info/METADATA
django_radius_nofuture-1.5.0.dev1.dist-info/WHEEL
django_radius_nofuture-1.5.0.dev1.dist-info/top_level.txt
django_radius_nofuture-1.5.0.dev1.dist-info/RECORD
